cosmopower_jax/__init__.py
cosmopower_jax/cosmopower_jax.py
cosmopower_jax/pca_utils/__init__.py
cosmopower_jax/pca_utils/cmb_pp_pca_transform_matrix.npy
cosmopower_jax/pca_utils/cmb_pp_training_mean.npy
cosmopower_jax/pca_utils/cmb_pp_training_std.npy
cosmopower_jax/pca_utils/cmb_te_pca_transform_matrix.npy
cosmopower_jax/pca_utils/cmb_te_training_mean.npy
cosmopower_jax/pca_utils/cmb_te_training_std.npy
cosmopower_jax/trained_models/__init__.py
cosmopower_jax/trained_models/cmb_ee.pkl
cosmopower_jax/trained_models/cmb_pp.pkl
cosmopower_jax/trained_models/cmb_te.pkl
cosmopower_jax/trained_models/cmb_tt.pkl
cosmopower_jax/trained_models/mpk_boost.pkl
cosmopower_jax/trained_models/mpk_lin.pkl
cosmopower_jax/trained_models/tf_cmb_template.npz
cosmopower_jax/trained_models/tf_cmb_template.pkl
cosmopower_jax/trained_models/tf_pca_template.npz
cosmopower_jax/trained_models/tf_pca_template.pkl
cosmopower_jax-0.5.7.dist-info/licenses/LICENSE
cosmopower_jax-0.5.7.dist-info/licenses/LICENSE_EXT
cosmopower_jax-0.5.7.dist-info/METADATA
cosmopower_jax-0.5.7.dist-info/WHEEL
cosmopower_jax-0.5.7.dist-info/top_level.txt
cosmopower_jax-0.5.7.dist-info/RECORD
