Metadata-Version: 2.4
Name: cosmopower_jax
Version: 0.5.7
Summary: Differentiable cosmological emulators
Home-page: https://github.com/dpiras/cosmopower-jax
Author: Davide Piras
Author-email: davide.piras@unige.ch
License: GNU General Public License v3.0 (GPLv3)
Classifier: Programming Language :: Python :: 3
Classifier: License :: OSI Approved :: GNU General Public License v3 (GPLv3)
Classifier: Operating System :: OS Independent
Requires-Python: >=3.9
License-File: LICENSE
License-File: LICENSE_EXT
Requires-Dist: jax
Requires-Dist: jaxlib
Requires-Dist: matplotlib>=3.1.2
Requires-Dist: numpy>=1.17.4
Dynamic: author
Dynamic: author-email
Dynamic: classifier
Dynamic: description
Dynamic: description-content-type
Dynamic: home-page
Dynamic: license
Dynamic: license-file
Dynamic: requires-dist
Dynamic: requires-python
Dynamic: summary
